RedisLibrary/RedisLibraryKeywords.py
RedisLibrary/__init__.py
RedisLibrary/version.py
robotframework_redislibrary-0.2.dist-info/METADATA
robotframework_redislibrary-0.2.dist-info/RECORD
robotframework_redislibrary-0.2.dist-info/WHEEL
robotframework_redislibrary-0.2.dist-info/top_level.txt
